AggFin/__init__.py
AggFin/auth.py
AggFin/config.py
AggFin/models.py
AggFin/version.py
AggFin/errors/__init__.py
AggFin/errors/handlers.py
AggFin/main/__init__.py
AggFin/main/routes.py
AggFin/users/__init-.py
AggFin/users/__init__.py
AggFin/users/forms.py
AggFin/users/routes.py
aggfindata-1.0.1.dist-info/LICENSE.txt
aggfindata-1.0.1.dist-info/METADATA
aggfindata-1.0.1.dist-info/WHEEL
aggfindata-1.0.1.dist-info/top_level.txt
aggfindata-1.0.1.dist-info/RECORD
