Metadata-Version: 2.1
Name: aggfindata
Version: 1.0.1
Summary: A Flask application for aggregating stock data and financial news
Author: Your Name
Author-email: your.email@example.com
Classifier: Programming Language :: Python :: 3
Classifier: Framework :: Flask
Classifier: License :: OSI Approved :: MIT License
Classifier: Operating System :: OS Independent
Requires-Python: >=3.8
License-File: LICENSE.txt
Requires-Dist: Flask==3.0.3
Requires-Dist: Flask-Login==0.6.2
Requires-Dist: Flask-Bcrypt==1.0.1
Requires-Dist: Flask-WTF==1.1.1
Requires-Dist: Flask-Mail==0.9.1
Requires-Dist: Flask-Migrate==4.1.0
Requires-Dist: Flask-SQLAlchemy==3.0.3
Requires-Dist: email-validator==2.0.0.post2
Requires-Dist: yfinance
Requires-Dist: requests
